octopyclient/__init__.py
octopyclient/__main__.py
octopyclient/common.py
octopyclient/idle_status.py
octopyclient/igtk.py
octopyclient/menu.py
octopyclient/octopyclient.py
octopyclient/print_menu.py
octopyclient/print_status.py
octopyclient/splash.py
octopyclient/ui.py
octopyclient/utils.py
octopyclient/octorest/__init__.py
octopyclient/octorest/octorest.py
octopyclient/panels/__init__.py
octopyclient/panels/control.py
octopyclient/panels/extrude.py
octopyclient/panels/fan.py
octopyclient/panels/files.py
octopyclient/panels/home.py
octopyclient/panels/move.py
octopyclient/panels/system.py
octopyclient/panels/temperature.py
octopyclient/styles/style2.css
octopyclient/styles/style320.css
octopyclient/styles/style480.css
octopyclient/styles/style800.css
octopyclient/styles/images/actions2.svg
octopyclient/styles/images/back.svg
octopyclient/styles/images/backspace.svg
octopyclient/styles/images/bed-level.svg
octopyclient/styles/images/bed.svg
octopyclient/styles/images/bed2.svg
octopyclient/styles/images/complete.svg
octopyclient/styles/images/control.svg
octopyclient/styles/images/control2.svg
octopyclient/styles/images/cool-down.svg
octopyclient/styles/images/custom-script.svg
octopyclient/styles/images/decrease.svg
octopyclient/styles/images/delete.svg
octopyclient/styles/images/extrude.svg
octopyclient/styles/images/extruder2.svg
octopyclient/styles/images/fan-off.svg
octopyclient/styles/images/fan-on.svg
octopyclient/styles/images/fan.svg
octopyclient/styles/images/filament.svg
octopyclient/styles/images/filament2.svg
octopyclient/styles/images/file.svg
octopyclient/styles/images/file2.svg
octopyclient/styles/images/files.svg
octopyclient/styles/images/finish.svg
octopyclient/styles/images/folder.svg
octopyclient/styles/images/heat-up.svg
octopyclient/styles/images/heat-up2.svg
octopyclient/styles/images/home-x.svg
octopyclient/styles/images/home-y.svg
octopyclient/styles/images/home-z.svg
octopyclient/styles/images/home.svg
octopyclient/styles/images/home2.svg
OctoPyClient-1.0.2.dist-info/LICENSE
OctoPyClient-1.0.2.dist-info/METADATA
OctoPyClient-1.0.2.dist-info/WHEEL
OctoPyClient-1.0.2.dist-info/entry_points.txt
OctoPyClient-1.0.2.dist-info/top_level.txt
OctoPyClient-1.0.2.dist-info/RECORD
