Metadata-Version: 2.1
Name: OctoPyClient
Version: 1.0.2
Summary: OctoPyClient - A touchscreen client for OctoPrint
Home-page: https://github.com/thess/OctoPyClient
Author: Ted Hess
Author-email: thess@kitschensync.net
Maintainer: Ted Hess
Maintainer-email: thess@kitschensync.net
License: LICENSE
Platform: UNKNOWN
Classifier: Programming Language :: Python :: 3
Classifier: License :: OSI Approved :: MIT License
Classifier: Operating System :: OS Independent
Requires-Python: >=3.6
Requires-Dist: PyGObject
Requires-Dist: attrs
Requires-Dist: humanize
Requires-Dist: psutil
Requires-Dist: pycairo
Requires-Dist: pyyaml
Requires-Dist: requests
Requires-Dist: sdnotify
Requires-Dist: urllib3
